dotm.py
dotm-1.0.1.dist-info/LICENSE
dotm-1.0.1.dist-info/METADATA
dotm-1.0.1.dist-info/WHEEL
dotm-1.0.1.dist-info/entry_points.txt
dotm-1.0.1.dist-info/top_level.txt
dotm-1.0.1.dist-info/RECORD
