Metadata-Version: 2.1
Name: dotm
Version: 1.0.1
Summary: dotm: Dotfiles Organized, Tracked, and Managed.
Author-email: "F. Y. BALABAN" <fyb@fybx.dev>
Project-URL: homepage, https://git.fybx.dev/fyb/dman
Project-URL: issues, https://github.com/fybx/dman/issues
Keywords: dotfiles,backup,CLI
Classifier: Development Status :: 5 - Production/Stable
Classifier: Programming Language :: Python :: 3
Classifier: Environment :: Console
Classifier: License :: OSI Approved :: GNU General Public License v2 (GPLv2)
Classifier: Operating System :: OS Independent
Classifier: Natural Language :: English
Classifier: Topic :: System :: Archiving
Classifier: Topic :: System
Classifier: Typing :: Typed
Requires-Python: >3.10
License-File: LICENSE
